zope.mkzeoinstance-6.0-py3.11-nspkg.pth
zope/mkzeoinstance/__init__.py
zope/mkzeoinstance/tests/__init__.py
zope/mkzeoinstance/tests/test_unix.py
zope.mkzeoinstance-6.0.dist-info/METADATA
zope.mkzeoinstance-6.0.dist-info/WHEEL
zope.mkzeoinstance-6.0.dist-info/entry_points.txt
zope.mkzeoinstance-6.0.dist-info/namespace_packages.txt
zope.mkzeoinstance-6.0.dist-info/top_level.txt
zope.mkzeoinstance-6.0.dist-info/RECORD
