Metadata-Version: 2.1
Name: zope.mkzeoinstance
Version: 6.0
Summary: Make standalone ZEO database server instances
Home-page: https://github.com/zopefoundation/zope.mkzeoinstance
Author: Zope Foundation and Contributors
Author-email: zope-dev@zope.dev
License: ZPL 2.1
Keywords: ZEO ZODB instance script
Classifier: Development Status :: 5 - Production/Stable
Classifier: Intended Audience :: Developers
Classifier: License :: OSI Approved :: Zope Public License
Classifier: Operating System :: OS Independent
Classifier: Programming Language :: Python
Classifier: Programming Language :: Python :: 3
Classifier: Programming Language :: Python :: 3.8
Classifier: Programming Language :: Python :: 3.9
Classifier: Programming Language :: Python :: 3.10
Classifier: Programming Language :: Python :: 3.11
Classifier: Programming Language :: Python :: 3.12
Classifier: Programming Language :: Python :: Implementation :: CPython
Requires-Python: >=3.8
Requires-Dist: setuptools
Requires-Dist: zdaemon
Requires-Dist: ZODB
Requires-Dist: ZEO
Provides-Extra: test
Requires-Dist: zope.testrunner; extra == "test"
